MANIFEST.in
README.txt
setup.py
docs/HISTORY.txt
docs/README.txt
src/ztfy/__init__.py
src/ztfy.gallery.egg-info/PKG-INFO
src/ztfy.gallery.egg-info/SOURCES.txt
src/ztfy.gallery.egg-info/dependency_links.txt
src/ztfy.gallery.egg-info/entry_points.txt
src/ztfy.gallery.egg-info/namespace_packages.txt
src/ztfy.gallery.egg-info/not-zip-safe
src/ztfy.gallery.egg-info/pkg-info
src/ztfy.gallery.egg-info/requires.txt
src/ztfy.gallery.egg-info/top_level.txt
src/ztfy/gallery/README.txt
src/ztfy/gallery/__init__.py
src/ztfy/gallery/configure.zcml
src/ztfy/gallery/database.py
src/ztfy/gallery/gallery.py
src/ztfy/gallery/gallery.zcml
src/ztfy/gallery/index.py
src/ztfy/gallery/index.zcml
src/ztfy/gallery/interfaces.py
src/ztfy/gallery/paragraph.py
src/ztfy/gallery/paypal.py
src/ztfy/gallery/paypal.zcml
src/ztfy/gallery/vocabulary.py
src/ztfy/gallery/browser/__init__.py
src/ztfy/gallery/browser/configure.zcml
src/ztfy/gallery/browser/gallery.py
src/ztfy/gallery/browser/gallery.zcml
src/ztfy/gallery/browser/index.py
src/ztfy/gallery/browser/index.zcml
src/ztfy/gallery/browser/paragraph.py
src/ztfy/gallery/browser/resources/css/gallery.back.css
src/ztfy/gallery/browser/resources/css/gallery.back.min.css
src/ztfy/gallery/browser/resources/img/index.png
src/ztfy/gallery/browser/resources/img/paypal-disabled.png
src/ztfy/gallery/browser/resources/img/paypal-enabled.png
src/ztfy/gallery/browser/resources/img/trash.png
src/ztfy/gallery/browser/resources/js/gallery.back.js
src/ztfy/gallery/browser/resources/js/gallery.back.min.js
src/ztfy/gallery/browser/templates/gallery_contents.pt
src/ztfy/gallery/browser/templates/image_diapo.pt
src/ztfy/gallery/browser/templates/index_contents.pt
src/ztfy/gallery/browser/templates/index_prefix.pt
src/ztfy/gallery/defaultskin/__init__.py
src/ztfy/gallery/defaultskin/configure.zcml
src/ztfy/gallery/defaultskin/gallery.py
src/ztfy/gallery/defaultskin/renderers/__init__.py
src/ztfy/gallery/defaultskin/renderers/configure.zcml
src/ztfy/gallery/defaultskin/renderers/default.pt
src/ztfy/gallery/defaultskin/renderers/default.py
src/ztfy/gallery/defaultskin/resources/css/ztfy.gallery.css
src/ztfy/gallery/defaultskin/resources/css/ztfy.gallery.min.css
src/ztfy/gallery/defaultskin/resources/img/caddie-sm.png
src/ztfy/gallery/defaultskin/resources/img/caddie.gif
src/ztfy/gallery/defaultskin/resources/img/caddie.png
